setup.cfg
setup.py
TOPSIS_Gautam_101816005.egg-info/PKG-INFO
TOPSIS_Gautam_101816005.egg-info/SOURCES.txt
TOPSIS_Gautam_101816005.egg-info/dependency_links.txt
TOPSIS_Gautam_101816005.egg-info/entry_points.txt
TOPSIS_Gautam_101816005.egg-info/requires.txt
TOPSIS_Gautam_101816005.egg-info/top_level.txt
source/topsis.py