Metadata-Version: 1.1
Name: TOPSIS-Gautam-101816005
Version: 1.0.1
Summary: This is a Python package to implement TOPSIS technique.
Home-page: https://pypi.org/project/TOPSIS-Gautam-101816005
Author: Gautam Thareja
Author-email: gthareja_be18@thapar.edu
License: MIT
Platform: UNKNOWN
Classifier: License :: OSI Approved :: MIT License
Classifier: Programming Language :: Python :: 3
Classifier: Programming Language :: Python :: 3.4
Classifier: Programming Language :: Python :: 3.5
Classifier: Programming Language :: Python :: 3.6
Classifier: Programming Language :: Python :: 3.7
